demo_proj_nvboard/Top.v
module Top(
    input  wire[7:0] IO_Addend_0,
    input  wire[7:0] IO_Addend_1,
    input  wire[7:0] IO_Addend_2,
    input  wire[7:0] IO_Addend_3,
    output wire[9:0] IO_Result
);

// Code here
// Sample:
wire [8:0] sumAddend_0_1 = IO_Addend_0 + IO_Addend_1; 
wire [8:0] sumAddend_2_3 = IO_Addend_2 + IO_Addend_3;
assign IO_Result = sumAddend_0_1 + sumAddend_2_3; 

endmodule

demo_proj/wave.vcd
$version Generated by VerilatedVcd $end
$date Tue Jul 18 20:09:00 2023
 $end
$timescale  10s $end

 $scope module top $end
  $var wire  8 # IO_Addend_0 [7:0] $end
  $var wire  8 $ IO_Addend_1 [7:0] $end
  $var wire  8 % IO_Addend_2 [7:0] $end
  $var wire  8 & IO_Addend_3 [7:0] $end
  $var wire 10 ' IO_Result [9:0] $end
  $scope module Top $end
   $var wire  8 # IO_Addend_0 [7:0] $end
   $var wire  8 $ IO_Addend_1 [7:0] $end
   $var wire  8 % IO_Addend_2 [7:0] $end
   $var wire  8 & IO_Addend_3 [7:0] $end
   $var wire 10 ' IO_Result [9:0] $end
   $var wire  9 ( sumAddend_0_1 [8:0] $end
   $var wire  9 ) sumAddend_2_3 [8:0] $end
  $upscope $end
 $upscope $end
$enddefinitions $end


#0
b00000000 #
b00000001 $
b00000010 %
b00000011 &
b0000000110 '
b000000001 (
b000000101 )
#1
b00000001 #
b00000010 $
b00000011 %
b00000100 &
b0000001010 '
b000000011 (
b000000111 )
#2
b00000010 #
b00000011 $
b00000100 %
b00000101 &
b0000001110 '
b000000101 (
b000001001 )
#3
b00000011 #
b00000100 $
b00000101 %
b00000110 &
b0000010010 '
b000000111 (
b000001011 )
#4
b00000100 #
b00000101 $
b00000110 %
b00000111 &
b0000010110 '
b000001001 (
b000001101 )
#5
b00000101 #
b00000110 $
b00000111 %
b00001000 &
b0000011010 '
b000001011 (
b000001111 )
#6
b00000110 #
b00000111 $
b00001000 %
b00001001 &
b0000011110 '
b000001101 (
b000010001 )
#7
b00000111 #
b00001000 $
b00001001 %
b00001010 &
b0000100010 '
b000001111 (
b000010011 )
#8
b00001000 #
b00001001 $
b00001010 %
b00001011 &
b0000100110 '
b000010001 (
b000010101 )
#9
b00001001 #
b00001010 $
b00001011 %
b00001100 &
b0000101010 '
b000010011 (
b000010111 )
#10
b00001010 #
b00001011 $
b00001100 %
b00001101 &
b0000101110 '
b000010101 (
b000011001 )
#11
b00001011 #
b00001100 $
b00001101 %
b00001110 &
b0000110010 '
b000010111 (
b000011011 )
#12
b00001100 #
b00001101 $
b00001110 %
b00001111 &
b0000110110 '
b000011001 (
b000011101 )
#13
b00001101 #
b00001110 $
b00001111 %
b00010000 &
b0000111010 '
b000011011 (
b000011111 )
#14
b00001110 #
b00001111 $
b00010000 %
b00010001 &
b0000111110 '
b000011101 (
b000100001 )
#15
b00001111 #
b00010000 $
b00010001 %
b00010010 &
b0001000010 '
b000011111 (
b000100011 )
#16
b00010000 #
b00010001 $
b00010010 %
b00010011 &
b0001000110 '
b000100001 (
b000100101 )
#17
b00010001 #
b00010010 $
b00010011 %
b00010100 &
b0001001010 '
b000100011 (
b000100111 )
#18
b00010010 #
b00010011 $
b00010100 %
b00010101 &
b0001001110 '
b000100101 (
b000101001 )
#19
b00010011 #
b00010100 $
b00010101 %
b00010110 &
b0001010010 '
b000100111 (
b000101011 )
